ReversedCodedSaltEncryption.py
rscencryption-0.1.0.dist-info/METADATA
rscencryption-0.1.0.dist-info/WHEEL
rscencryption-0.1.0.dist-info/top_level.txt
rscencryption-0.1.0.dist-info/RECORD
