Metadata-Version: 2.1
Name: rscencryption
Version: 0.1.0
Summary: Library for the RCSE
Author: Ava Info Conseils
License: AVA IC
